README.rst
setup.py
lunar/__init__.py
lunar/database.py
lunar/lunar.py
lunar/router.py
lunar/server.py
lunar/template.py
lunar/wrappers.py
lunar.egg-info/PKG-INFO
lunar.egg-info/SOURCES.txt
lunar.egg-info/dependency_links.txt
lunar.egg-info/top_level.txt