Metadata-Version: 1.1
Name: lunar
Version: 0.0.1
Summary: lunar is a WSGI based webframework in pure Python, without any third-party dependency.
Home-page: UNKNOWN
Author: jasonlyu
Author-email: jasonlvhit@gmail.com
License: UNKNOWN
Platform: UNKNOWN
Classifier: Environment :: Web Environment
Classifier: Intended Audience :: Developers
Classifier: Operating System :: OS Independent
Classifier: Programming Language :: Python
Classifier: Topic :: Internet :: WWW/HTTP :: Dynamic Content
Classifier: Topic :: Software Development :: Libraries :: Python Modules
